{
  "nombre": "Agricolaocoa",
  "cerros": [
    {
      "nombre": "CerroTunel",
      "sectores": [
	"AO-CERRO 1-BCLONAL B-V011",
        "AO-CERRO 1-BCLONAL B-V012",
        "AO-CERRO 1-BCLONAL B-V010",
        "AO-CERRO 1-BCLONAL A 2021-A",
        "AO-CERRO 1-BCLONAL A 2017",
        "AO-CERRO 1-BCLONAL A 2016",
        "AO-CERRO 1-B1B-V001",
        "AO-CERRO 1-B4B-V009",
        "AO-CERRO 1-B4B-V008",
        "AO-CERRO 1-B4B-V007",
        "AO-CERRO 1-B4B-V006",
        "AO-CERRO 1-B4B-V005",
        "AO-CERRO 1-B4B-V004",
        "AO-CERRO 1-B4B-V003",
        "AO-CERRO 1-B4B-V002",
        "AO-CERRO 1-B4B-V001",
        "AO-CERRO 1-B3B-V009",
        "AO-CERRO 1-B3B-V008",
        "AO-CERRO 1-B3B-V007",
        "AO-CERRO 1-B3B-V006",
        "AO-CERRO 1-B3B-V005",
        "AO-CERRO 1-B3B-V004",
        "AO-CERRO 1-B3B-V003",
        "AO-CERRO 1-B3B-V002",
        "AO-CERRO 1-B3B-V001",
        "AO-CERRO 1-B2B-V009",
        "AO-CERRO 1-B2B-V008",
        "AO-CERRO 1-B2B-V007",
        "AO-CERRO 1-B2B-V006",
        "AO-CERRO 1-B2B-V005",
        "AO-CERRO 1-B2B-V004",
        "AO-CERRO 1-B2B-V003",
        "AO-CERRO 1-B2B-V002",
        "AO-CERRO 1-B2B-V001",
        "AO-CERRO 1-B1B-V009",
        "AO-CERRO 1-B1B-V008",
        "AO-CERRO 1-B1B-V007",
        "AO-CERRO 1-B1B-V006",
        "AO-CERRO 1-B1B-V005",
        "AO-CERRO 1-B1B-V004",
        "AO-CERRO 1-B1B-V003",
        "AO-CERRO 1-B1B-V002",
        "AO-CERRO 1-B3A-V007",
        "AO-CERRO 1-B4A-V006",
        "AO-CERRO 1-B4A-V005",
        "AO-CERRO 1-B4A-V004",
        "AO-CERRO 1-B4A-V003",
        "AO-CERRO 1-B4A-V002",
        "AO-CERRO 1-B4A-V001",
        "AO-CERRO 1-B3A-V006",
        "AO-CERRO 1-B3A-V005",
        "AO-CERRO 1-B3A-V004",
        "AO-CERRO 1-B3A-V003",
        "AO-CERRO 1-B3A-V002",
        "AO-CERRO 1-B3A-V001",
        "AO-CERRO 1-B2A-V14",
        "AO-CERRO 1-B2A-V013",
        "AO-CERRO 1-B2A-V012",
        "AO-CERRO 1-B2A-V011",
        "AO-CERRO 1-B2A-V010",
        "AO-CERRO 1-B2A-V009",
        "AO-CERRO 1-B2A-V008",
        "AO-CERRO 1-B2A-V007",
        "AO-CERRO 1-B2A-V006",
        "AO-CERRO 1-B2A-V005",
        "AO-CERRO 1-B2A-V004",
        "AO-CERRO 1-B2A-V003",
        "AO-CERRO 1-B2A-V002",
        "AO-CERRO 1-B2A-V001",
        "AO-CERRO 1-B1A-V011",
        "AO-CERRO 1-B1A-V010",
        "AO-CERRO 1-B1A-V009",
        "AO-CERRO 1-B1A-V008",
        "AO-CERRO 1-B1A-V007",
        "AO-CERRO 1-B1A-V006",
        "AO-CERRO 1-B1A-V005",
        "AO-CERRO 1-B1A-V004",
        "AO-CERRO 1-B1A-V003",
        "AO-CERRO 1-B1A-V002",
        "AO-CERRO 1-B1A-V001",
        "AO-CERRO 2-B1D-V003.1",
        "AO-CERRO 2-B1D-V001.15",
        "AO-CERRO 2-B1D-V006.1",
        "AO-CERRO 2-B1D-V005.1",
        "AO-CERRO 2-B1D-V004.1",
        "AO-CERRO 2-B1C-V0013.1",
        "AO-CERRO 2-B1C-V0022.2",
        "AO-CERRO 2-B1C-V0022.1",
        "AO-CERRO 2-B1C-V0021.1",
        "AO-CERRO 2-B1C-V0020.1",
        "AO-CERRO 2-B1C-V0019.1",
        "AO-CERRO 2-B1C-V0017.2",
        "AO-CERRO 2-B1C-V0017.1",
        "AO-CERRO 2-B1C-V0016.1",
        "AO-CERRO 2-B1C-V0015.1",
        "AO-CERRO 2-B1C-V0014.1",
        "AO-CERRO 3-B4-V0018",
        "AO-CERRO 3-B4-V0017",
        "AO-CERRO 3-B4-V0016",
        "AO-CERRO 3-B4-V0015",
        "AO-CERRO 3-B4-V0014",
        "AO-CERRO 3-B4-V0013",
        "AO-CERRO 3-B4-V0012",
        "AO-CERRO 3-B4-V0011",
        "AO-CERRO 3-B4-V0010",
        "AO-CERRO 3-B4-V009",
        "AO-CERRO 3-B3-V0018",
        "AO-CERRO 3-B3-V015",
        "AO-CERRO 3-B3-V012-14",
        "AO-CERRO 3-B3-V0011",
        "AO-CERRO 3-B3-V010",
        "AO-CERRO 3-B2-V019-20",
        "AO-CERRO 3-B2-V005-6-8",
        "AO-CERRO 3-B2-V004",
        "AO-CERRO 3-B2-V003",
        "AO-CERRO 3-B2-V002",
        "AO-CERRO 3-B2-V001",
        "AO-CERRO 3-B1-V020",
        "AO-CERRO 3-B1-V019",
        "AO-CERRO 3-B1-V017",
        "AO-CERRO 3-B1-V016",
        "AO-CERRO 3-B1-V009",
        "AO-CERRO 3-B1-V008",
        "AO-CERRO 3-B1-V007",
        "AO-CERRO 3-B1-V006",
        "AO-CERRO 3-B1-V005",
        "AO-CERRO 3-B1-V004",
        "AO-CERRO 3-B1-V001-2-3",
        "AO-CERRO 2-B1B-V006.1",
        "AO-CERRO 2-B1B-V005.1",
        "AO-CERRO 2-B1B-V0011.1",
        "AO-CERRO 2-B1B-V0010.1",
        "AO-CERRO 2-B1B-V009.1",
        "AO-CERRO 2-B1B-V008.1",
        "AO-CERRO 2-B1B-V007.1",
        "AO-CERRO 2-B1B-V004.1",
        "AO-CERRO 2-B1B-V003.1",
        "AO-CERRO 2-B1B-V002.1",
        "AO-CERRO 2-B1B-V001.1",
        "AO-CERRO 2-B1A-V007.1",
        "AO-CERRO 2-B1A-V0014.1",
        "AO-CERRO 2-B1A-V002.1",
        "AO-CERRO 2-B1A-V001.1",
        "AO-CERRO 2-B1A-V0013.1",
        "AO-CERRO 2-B1A-V0012.1",
        "AO-CERRO 2-B1A-V0011.1",
        "AO-CERRO 2-B1A-V0010.1",
        "AO-CERRO 2-B1A-V009.1",
        "AO-CERRO 2-B1A-V008.1"
	]
    },
    {
      "nombre": "CerroCasa",
      "sectores": [
       "ARM-CASA-B1-V005",
        "ARM-CASA-B1-V004",
        "ARM-CASA-B1-V003",
        "ARM-CASA-B1-V002",
        "ARM-CASA-B1-V001",
        "RH-PRINCIPIO 2-B3-V016",
        "RH-PRINCIPIO 2-B3-V015",
        "RH-PRINCIPIO 2-B3-V014",
        "RH-PRINCIPIO 2-B3-V013",
        "RH-PRINCIPIO 2-B3-V012",
        "RH-PRINCIPIO 2-B3-V011",
        "RH-PRINCIPIO 2-B3-V010",
        "AO-PRINCIPIO 2-B2-V009",
        "AO-PRINCIPIO 2-B2-V008",
        "AO-PRINCIPIO 2-B2-V007",
        "AO-PRINCIPIO 2-B2-V006",
        "AO-PRINCIPIO 2-B2-V005",
        "AO-PRINCIPIO 1-B1-V004",
        "AO-PRINCIPIO 1-B1-V003",
        "AO-PRINCIPIO 1-B1-V002",
        "AO-PRINCIPIO 1-B1-V001",
        "AO-CerroCasa-BC6-V120",
        "AO-CerroCasa-BC6-V119",
        "AO-CerroCasa-BC6-V118",
        "AO-CerroCasa-BC6-V117",
        "AO-CerroCasa-BC6-V116",
        "AO-CerroCasa-BC5-V101",
        "AO-CerroCasa-BC6-V115",
        "AO-CerroCasa-BC5-V100",
        "AO-CerroCasa-BC5-V099",
        "AO-CerroCasa-BC5-V098",
        "AO-CerroCasa-BC5-V097",
        "AO-CerroCasa-BC5-V096",
        "AO-CerroCasa-BC5-V095",
        "AO-CerroCasa-BC5-V094",
        "AO-CerroCasa-BC5-V093",
        "AO-CerroCasa-BC5-V092",
        "AO-CerroCasa-BC3-V045",
        "AO-CerroCasa-BC3-V044",
        "AO-CerroCasa-BC3-V043",
        "AO-CerroCasa-BB6-V114",
        "AO-CerroCasa-BB6-V113",
        "AO-CerroCasa-BB6-V112",
        "AO-CerroCasa-BB6-V111",
        "AO-CerroCasa-BB6-V110",
        "AO-CerroCasa-BB6-V109",
        "AO-CerroCasa-BB6-V108",
        "AO-CerroCasa-BB5-V091",
        "AO-CerroCasa-BB5-V090",
        "AO-CerroCasa-BB5-V089",
        "AO-CerroCasa-BB5-V088",
        "AO-CerroCasa-BB5-V087",
        "AO-CerroCasa-BB5-V083",
        "AO-CerroCasa-BB3-V042",
        "AO-CerroCasa-BB3-V041",
        "AO-CerroCasa-BB3-V040",
        "AO-CerroCasa-BB3-V039",
        "AO-CerroCasa-BB3-V038",
        "AO-CerroCasa-BA6-V107",
        "AO-CerroCasa-BA6-V106",
        "AO-CerroCasa-BA6-V105",
        "AO-CerroCasa-BA6-V104",
        "AO-CerroCasa-BA6-V103",
        "AO-CerroCasa-BA6-V102",
        "AO-CerroCasa-BA5-V086",
        "AO-CerroCasa-BA5-V085",
        "AO-CerroCasa-BA5-V084",
        "AO-CerroCasa-BA5-V082",
        "AO-CerroCasa-BA5-V081",
        "AO-CerroCasa-BA5-V080",
        "AO-CerroCasa-BA5-V079",
        "AO-CerroCasa-BA5-V078",
        "AO-CerroCasa-BA5-V077",
        "AO-CerroCasa-BA5-V076",
        "AO-CerroCasa-BA5-V075",
        "AO-CerroCasa-BA5-V074",
        "AO-CerroCasa-BA5-V073",
        "AO-CerroCasa-BC4-V072",
        "AO-CerroCasa-BC4-V071",
        "AO-CerroCasa-BC4-V070",
        "AO-CerroCasa-BC4-V069",
        "AO-CerroCasa-BC4-V068",
        "AO-CerroCasa-BC4-V067",
        "AO-CerroCasa-BC4-V066",
        "AO-CerroCasa-BC4-V065",
        "AO-CerroCasa-BC4-V064",
        "AO-CerroCasa-BC2-V032",
        "AO-CerroCasa-BC2-V031",
        "AO-CerroCasa-BC2-V030",
        "AO-CerroCasa-BC2-V029",
        "AO-CerroCasa-BC2-V028",
        "AO-CerroCasa-BC1-V014",
        "AO-CerroCasa-BC1-V013",
        "AO-CerroCasa-BC1-V012",
        "AO-CerroCasa-BC1-V011",
        "AO-CerroCasa-BB4-V063",
        "AO-CerroCasa-BB4-V062",
        "AO-CerroCasa-BB4-V061",
        "AO-CerroCasa-BB4-V060",
        "AO-CerroCasa-BB4-V059",
        "AO-CerroCasa-BB4-V058",
        "AO-CerroCasa-BB4-V057",
        "AO-CerroCasa-BB4-V056",
        "AO-CerroCasa-BB4-V055",
        "AO-CerroCasa-BA2-V027",
        "AO-CerroCasa-BA2-V026",
        "AO-CerroCasa-BA2-V025",
        "AO-CerroCasa-BA2-V024",
        "AO-CerroCasa-BA2-V023",
        "AO-CerroCasa-BA2-V022",
        "AO-CerroCasa-BB1-V010",
        "AO-CerroCasa-BB1-V008",
        "AO-CerroCasa-BB1-V009",
        "AO-CerroCasa-BB1-V007",
        "AO-CerroCasa-BB1-V006",
        "AO-CerroCasa-BA1-V001",
        "AO-CerroCasa-BA4-V054",
        "AO-CerroCasa-BA4-V053",
        "AO-CerroCasa-BA4-V052",
        "AO-CerroCasa-BA4-V051",
        "AO-CerroCasa-BA4-V050",
        "AO-CerroCasa-BA4-V049",
        "AO-CerroCasa-BA4-V048",
        "AO-CerroCasa-BA4-V047",
        "AO-CerroCasa-BA4-V046",
        "AO-CerroCasa-BA3-V037",
        "AO-CerroCasa-BA3-V036",
        "AO-CerroCasa-BA3-V035",
        "AO-CerroCasa-BA3-V034",
        "AO-CerroCasa-BA3-V033",
        "AO-CerroCasa-BA2-V021",
        "AO-CerroCasa-BA2-V020",
        "AO-CerroCasa-BA2-V019",
        "AO-CerroCasa-BA2-V018",
        "AO-CerroCasa-BA2-V017",
        "AO-CerroCasa-BA2-V016",
        "AO-CerroCasa-BA2-V015",
        "AO-CerroCasa-BB1-V005",
        "AO-CerroCasa-BA1-V004",
        "AO-CerroCasa-BA1-V003",
        "AO-CerroCasa-BA1-V002"
]
    },
    {
      "nombre": "LaEsperanza",
      "sectores": [
    "AO-Lote B-B1-V001",
    "AO-Lote B-B2-V002",
    "AO-BCO-BA-V001",
    "AO-BCO-BB-V010",
    "AO-BCO-BB-V009",
    "AO-BCO-BB-V008",
    "AO-BCO-BB-V007",
    "AO-BCO-BB-V006",
    "AO-BCO-BPARCELA 15-V011",
    "AO-BCO-BPARCELA 15-V013",
    "AO-BCO-BPARCELA 15-V015",
    "AO-BCO-BPARCELA 15-V014",
    "AO-BCO-BPARCELA 15-V012",
    "AO-BCO-BA-V005",
    "AO-BCO-BA-V004",
    "AO-BCO-BA-V003",
    "AO-BCO-BA-V002",
    "AO-PALTOS FLORES-B1-V001",
    "AO-PALTOS FLORES-B3-V011",
    "AO-PALTOS FLORES-B3-V010",
    "AO-PALTOS FLORES-B3-V009",
    "AO-PALTOS FLORES-B3-V008",
    "AO-PALTOS FLORES-B2-V007",
    "AO-PALTOS FLORES-B2-V006",
    "AO-PALTOS FLORES-B2-V005",
    "AO-PALTOS FLORES-B1-V004",
    "AO-PALTOS FLORES-B1-V003",
    "AO-PALTOS FLORES-B1-V002",
    "AO-Sector Caldera-V001",
    "AO-AG.RM-HUERTO RM-B3 Y 4",
    "AO-Sector Caldera-V006",
    "AO-Sector Caldera-V005",
    "AO-Sector Caldera-V004",
    "AO-Sector Caldera-V003",
    "AO-Sector Caldera-V002",
    "AO-Detras Caseta-BDC",
    "AO-Sector La Isla (Caseta Nueva)",
    "AO-ARC-RIO-BISLA",
    "AO-ARC-RIO-BE",
    "AO-ARC-RIO-B3",
    "AO-ARC-RIO-B2",
    "ARC-RIO-B5",
    "AO-ARC-RIO-BPN",
    "AO-AG.RM-HUERTO RM-B5",
    "AO-AG.RM-HUERTO RM-BLÍNEA",
    "AO-AG.RM-HUERTO RM-B5 Y 6",
    "AO-AG.RM-HUERTO RM-B3 SIN/C",
    "AO-AG.RM-HUERTO RM-B3 CON/C",
    "AO-MRC-H. MRC-LADERAS",
    "AO-EX_GWEN-V000 (Caseta Nueva)",
    "AO-MRC-H. MRC-B4",
    "AO-MRC-H. MRC-BOFIC.",
    "AO-MRC-H. MRC-BTRANQUE NUEVO",
    "AO-MRC-H. MRC-BBAJO TRANQUE",
    "AO-MRC-H. MRC-BRULO"
]
    }
  ]
}